pokapi/__init__.py
pokapi/exceptions.py
pokapi/folio.py
pokapi/record.py
pokapi-0.4.0.dist-info/LICENSE
pokapi-0.4.0.dist-info/METADATA
pokapi-0.4.0.dist-info/WHEEL
pokapi-0.4.0.dist-info/top_level.txt
pokapi-0.4.0.dist-info/RECORD
