Metadata-Version: 2.1
Name: pokapi
Version: 0.4.0
Summary: Python package for getting basic data from a FOLIO LSP server
Home-page: https://github.com/caltechlibrary/pokapi
Author: Michael Hucka
Author-email: mhucka@caltech.edu
License: BSD 3-clause
Project-URL: Source Code, https://github.com/caltechlibrary/pokapi
Project-URL: Bug Tracker, https://github.com/caltechlibrary/pokapi/issues
Keywords: Python,utilities
Platform: UNKNOWN
Classifier: Development Status :: 3 - Alpha
Classifier: Intended Audience :: Science/Research
Classifier: License :: OSI Approved :: BSD License
Classifier: Operating System :: MacOS :: MacOS X
Classifier: Operating System :: Microsoft :: Windows
Classifier: Operating System :: POSIX
Classifier: Operating System :: POSIX :: Linux
Classifier: Operating System :: Unix
Classifier: Programming Language :: Python
Classifier: Programming Language :: Python :: 3.8
Requires-Python: >=3.8
Requires-Dist: commonpy (>=1.9.5)
Requires-Dist: lxml (>=4.9.1)
Requires-Dist: python-decouple (>=3.6)
Requires-Dist: sidetrack (>=2.0.0)
Requires-Dist: uritemplate (>=4.1.0)
Requires-Dist: validators (>=0.20.0)
Provides-Extra: dev
